{"Squid Order":{"choice":{"name":"SO","value":"SO"}},"SplatLock":{"choice":{"name":"SL","value":"SL"}},"Squid Order : Nouvelle vague":{"choice":{"name":"SONV","value":"SONV"}},"Palette Estivale":{"choice":{"name":"PE","value":"PE"}},"Imitations":{"choice":{"name":"FAKE","value":"FAKE"}},"Promesses de la surface":{"choice":{"name":"PS","value":"PS"}},"Voeux des profondeurs":{"choice":{"name":"VP","value":"VP"}},"Palette Merveille":{"choice":{"name":"PM","value":"PM"}},"Saké.":{"choice":{"name":"SAKE","value":"SAKE"}},"Aube Radieuse":{"choice":{"name":"AR","value":"AR"}}}